Metadata-Version: 2.1
Name: strangeworks-python-core
Version: 0.1.7
Summary: Strangeworks Core provides the infrastructure to interact with the platform.
License: Apache-2.0
Author: Strange Devs
Author-email: hello@strangeworks.com
Requires-Python: >=3.9,<4.0
Classifier: License :: OSI Approved :: Apache Software License
Classifier: Programming Language :: Python :: 3
Classifier: Programming Language :: Python :: 3.9
Classifier: Programming Language :: Python :: 3.10
Classifier: Programming Language :: Python :: 3.11
Requires-Dist: gql (>=3.4.0,<4.0.0)
Requires-Dist: requests (>=2.28.2,<3.0.0)
Requires-Dist: requests-toolbelt (>=1.0.0,<2.0.0)
Requires-Dist: tomlkit (>=0.11.6,<0.12.0)
